[
  
  {
    "id": "9852",
    "url": "https://asia.pokemon-card.com/tw/card-search/detail/9852/",
    "imgUrl": "https://asia.pokemon-card.com/tw/card-img/tw00009852.png"
  },
  {
    "id": "9853",
    "url": "https://asia.pokemon-card.com/tw/card-search/detail/9853/",
    "imgUrl": "https://asia.pokemon-card.com/tw/card-img/tw00009853.png"
  },
  {
    "id": "9854",
    "url": "https://asia.pokemon-card.com/tw/card-search/detail/9854/",
    "imgUrl": "https://asia.pokemon-card.com/tw/card-img/tw00009854.png"
  },
  {
    "id": "9855",
    "url": "https://asia.pokemon-card.com/tw/card-search/detail/9855/",
    "imgUrl": "https://asia.pokemon-card.com/tw/card-img/tw00009855.png"
  },
  {
    "id": "9856",
    "url": "https://asia.pokemon-card.com/tw/card-search/detail/9856/",
    "imgUrl": "https://asia.pokemon-card.com/tw/card-img/tw00009856.png"
  },
  {
    "id": "9857",
    "url": "https://asia.pokemon-card.com/tw/card-search/detail/9857/",
    "imgUrl": "https://asia.pokemon-card.com/tw/card-img/tw00009857.png"
  },
  {
    "id": "9858",
    "url": "https://asia.pokemon-card.com/tw/card-search/detail/9858/",
    "imgUrl": "https://asia.pokemon-card.com/tw/card-img/tw00009858.png"
  },
  {
    "id": "9859",
    "url": "https://asia.pokemon-card.com/tw/card-search/detail/9859/",
    "imgUrl": "https://asia.pokemon-card.com/tw/card-img/tw00009859.png"
  },
  {
    "id": "9860",
    "url": "https://asia.pokemon-card.com/tw/card-search/detail/9860/",
    "imgUrl": "https://asia.pokemon-card.com/tw/card-img/tw00009860.png"
  },
  {
    "id": "9861",
    "url": "https://asia.pokemon-card.com/tw/card-search/detail/9861/",
    "imgUrl": "https://asia.pokemon-card.com/tw/card-img/tw00009861.png"
  },
  {
    "id": "9862",
    "url": "https://asia.pokemon-card.com/tw/card-search/detail/9862/",
    "imgUrl": "https://asia.pokemon-card.com/tw/card-img/tw00009862.png"
  },
  {
    "id": "9863",
    "url": "https://asia.pokemon-card.com/tw/card-search/detail/9863/",
    "imgUrl": "https://asia.pokemon-card.com/tw/card-img/tw00009863.png"
  },
  {
    "id": "9864",
    "url": "https://asia.pokemon-card.com/tw/card-search/detail/9864/",
    "imgUrl": "https://asia.pokemon-card.com/tw/card-img/tw00009864.png"
  },
  {
    "id": "9865",
    "url": "https://asia.pokemon-card.com/tw/card-search/detail/9865/",
    "imgUrl": "https://asia.pokemon-card.com/tw/card-img/tw00009865.png"
  },
  {
    "id": "9866",
    "url": "https://asia.pokemon-card.com/tw/card-search/detail/9866/",
    "imgUrl": "https://asia.pokemon-card.com/tw/card-img/tw00009866.png"
  },
  {
    "id": "9867",
    "url": "https://asia.pokemon-card.com/tw/card-search/detail/9867/",
    "imgUrl": "https://asia.pokemon-card.com/tw/card-img/tw00009867.png"
  },
  {
    "id": "9868",
    "url": "https://asia.pokemon-card.com/tw/card-search/detail/9868/",
    "imgUrl": "https://asia.pokemon-card.com/tw/card-img/tw00009868.png"
  },
  {
    "id": "9869",
    "url": "https://asia.pokemon-card.com/tw/card-search/detail/9869/",
    "imgUrl": "https://asia.pokemon-card.com/tw/card-img/tw00009869.png"
  },
  {
    "id": "9870",
    "url": "https://asia.pokemon-card.com/tw/card-search/detail/9870/",
    "imgUrl": "https://asia.pokemon-card.com/tw/card-img/tw00009870.png"
  },
  {
    "id": "9871",
    "url": "https://asia.pokemon-card.com/tw/card-search/detail/9871/",
    "imgUrl": "https://asia.pokemon-card.com/tw/card-img/tw00009871.png"
  },
  {
    "id": "9872",
    "url": "https://asia.pokemon-card.com/tw/card-search/detail/9872/",
    "imgUrl": "https://asia.pokemon-card.com/tw/card-img/tw00009872.png"
  },
  {
    "id": "9873",
    "url": "https://asia.pokemon-card.com/tw/card-search/detail/9873/",
    "imgUrl": "https://asia.pokemon-card.com/tw/card-img/tw00009873.png"
  },
  {
    "id": "9874",
    "url": "https://asia.pokemon-card.com/tw/card-search/detail/9874/",
    "imgUrl": "https://asia.pokemon-card.com/tw/card-img/tw00009874.png"
  },
  {
    "id": "9875",
    "url": "https://asia.pokemon-card.com/tw/card-search/detail/9875/",
    "imgUrl": "https://asia.pokemon-card.com/tw/card-img/tw00009875.png"
  },
  {
    "id": "9876",
    "url": "https://asia.pokemon-card.com/tw/card-search/detail/9876/",
    "imgUrl": "https://asia.pokemon-card.com/tw/card-img/tw00009876.png"
  },
  {
    "id": "9877",
    "url": "https://asia.pokemon-card.com/tw/card-search/detail/9877/",
    "imgUrl": "https://asia.pokemon-card.com/tw/card-img/tw00009877.png"
  },
  {
    "id": "9878",
    "url": "https://asia.pokemon-card.com/tw/card-search/detail/9878/",
    "imgUrl": "https://asia.pokemon-card.com/tw/card-img/tw00009878.png"
  },
  {
    "id": "9879",
    "url": "https://asia.pokemon-card.com/tw/card-search/detail/9879/",
    "imgUrl": "https://asia.pokemon-card.com/tw/card-img/tw00009879.png"
  },
  {
    "id": "9880",
    "url": "https://asia.pokemon-card.com/tw/card-search/detail/9880/",
    "imgUrl": "https://asia.pokemon-card.com/tw/card-img/tw00009880.png"
  },
  {
    "id": "9881",
    "url": "https://asia.pokemon-card.com/tw/card-search/detail/9881/",
    "imgUrl": "https://asia.pokemon-card.com/tw/card-img/tw00009881.png"
  },
  {
    "id": "9882",
    "url": "https://asia.pokemon-card.com/tw/card-search/detail/9882/",
    "imgUrl": "https://asia.pokemon-card.com/tw/card-img/tw00009882.png"
  },
  {
    "id": "9883",
    "url": "https://asia.pokemon-card.com/tw/card-search/detail/9883/",
    "imgUrl": "https://asia.pokemon-card.com/tw/card-img/tw00009883.png"
  },
  {
    "id": "9884",
    "url": "https://asia.pokemon-card.com/tw/card-search/detail/9884/",
    "imgUrl": "https://asia.pokemon-card.com/tw/card-img/tw00009884.png"
  },
  {
    "id": "9885",
    "url": "https://asia.pokemon-card.com/tw/card-search/detail/9885/",
    "imgUrl": "https://asia.pokemon-card.com/tw/card-img/tw00009885.png"
  },
  {
    "id": "9886",
    "url": "https://asia.pokemon-card.com/tw/card-search/detail/9886/",
    "imgUrl": "https://asia.pokemon-card.com/tw/card-img/tw00009886.png"
  },
  {
    "id": "9887",
    "url": "https://asia.pokemon-card.com/tw/card-search/detail/9887/",
    "imgUrl": "https://asia.pokemon-card.com/tw/card-img/tw00009887.png"
  },
  {
    "id": "9888",
    "url": "https://asia.pokemon-card.com/tw/card-search/detail/9888/",
    "imgUrl": "https://asia.pokemon-card.com/tw/card-img/tw00009888.png"
  },
  {
    "id": "9889",
    "url": "https://asia.pokemon-card.com/tw/card-search/detail/9889/",
    "imgUrl": "https://asia.pokemon-card.com/tw/card-img/tw00009889.png"
  },
  {
    "id": "9890",
    "url": "https://asia.pokemon-card.com/tw/card-search/detail/9890/",
    "imgUrl": "https://asia.pokemon-card.com/tw/card-img/tw00009890.png"
  },
  {
    "id": "9891",
    "url": "https://asia.pokemon-card.com/tw/card-search/detail/9891/",
    "imgUrl": "https://asia.pokemon-card.com/tw/card-img/tw00009891.png"
  },
  {
    "id": "9892",
    "url": "https://asia.pokemon-card.com/tw/card-search/detail/9892/",
    "imgUrl": "https://asia.pokemon-card.com/tw/card-img/tw00009892.png"
  },
  {
    "id": "9893",
    "url": "https://asia.pokemon-card.com/tw/card-search/detail/9893/",
    "imgUrl": "https://asia.pokemon-card.com/tw/card-img/tw00009893.png"
  },
  {
    "id": "9894",
    "url": "https://asia.pokemon-card.com/tw/card-search/detail/9894/",
    "imgUrl": "https://asia.pokemon-card.com/tw/card-img/tw00009894.png"
  },
  {
    "id": "9895",
    "url": "https://asia.pokemon-card.com/tw/card-search/detail/9895/",
    "imgUrl": "https://asia.pokemon-card.com/tw/card-img/tw00009895.png"
  },
  {
    "id": "9896",
    "url": "https://asia.pokemon-card.com/tw/card-search/detail/9896/",
    "imgUrl": "https://asia.pokemon-card.com/tw/card-img/tw00009896.png"
  },
  {
    "id": "9897",
    "url": "https://asia.pokemon-card.com/tw/card-search/detail/9897/",
    "imgUrl": "https://asia.pokemon-card.com/tw/card-img/tw00009897.png"
  },
  {
    "id": "9898",
    "url": "https://asia.pokemon-card.com/tw/card-search/detail/9898/",
    "imgUrl": "https://asia.pokemon-card.com/tw/card-img/tw00009898.png"
  },
  {
    "id": "9899",
    "url": "https://asia.pokemon-card.com/tw/card-search/detail/9899/",
    "imgUrl": "https://asia.pokemon-card.com/tw/card-img/tw00009899.png"
  },
  {
    "id": "9900",
    "url": "https://asia.pokemon-card.com/tw/card-search/detail/9900/",
    "imgUrl": "https://asia.pokemon-card.com/tw/card-img/tw00009900.png"
  },
  {
    "id": "9901",
    "url": "https://asia.pokemon-card.com/tw/card-search/detail/9901/",
    "imgUrl": "https://asia.pokemon-card.com/tw/card-img/tw00009901.png"
  },
  {
    "id": "9902",
    "url": "https://asia.pokemon-card.com/tw/card-search/detail/9902/",
    "imgUrl": "https://asia.pokemon-card.com/tw/card-img/tw00009902.png"
  },
  {
    "id": "9903",
    "url": "https://asia.pokemon-card.com/tw/card-search/detail/9903/",
    "imgUrl": "https://asia.pokemon-card.com/tw/card-img/tw00009903.png"
  },
  {
    "id": "9904",
    "url": "https://asia.pokemon-card.com/tw/card-search/detail/9904/",
    "imgUrl": "https://asia.pokemon-card.com/tw/card-img/tw00009904.png"
  },
  {
    "id": "9905",
    "url": "https://asia.pokemon-card.com/tw/card-search/detail/9905/",
    "imgUrl": "https://asia.pokemon-card.com/tw/card-img/tw00009905.png"
  },
  {
    "id": "9906",
    "url": "https://asia.pokemon-card.com/tw/card-search/detail/9906/",
    "imgUrl": "https://asia.pokemon-card.com/tw/card-img/tw00009906.png"
  },
  {
    "id": "9907",
    "url": "https://asia.pokemon-card.com/tw/card-search/detail/9907/",
    "imgUrl": "https://asia.pokemon-card.com/tw/card-img/tw00009907.png"
  },
  {
    "id": "9908",
    "url": "https://asia.pokemon-card.com/tw/card-search/detail/9908/",
    "imgUrl": "https://asia.pokemon-card.com/tw/card-img/tw00009908.png"
  },
  {
    "id": "9909",
    "url": "https://asia.pokemon-card.com/tw/card-search/detail/9909/",
    "imgUrl": "https://asia.pokemon-card.com/tw/card-img/tw00009909.png"
  },
  {
    "id": "9910",
    "url": "https://asia.pokemon-card.com/tw/card-search/detail/9910/",
    "imgUrl": "https://asia.pokemon-card.com/tw/card-img/tw00009910.png"
  },
  {
    "id": "9911",
    "url": "https://asia.pokemon-card.com/tw/card-search/detail/9911/",
    "imgUrl": "https://asia.pokemon-card.com/tw/card-img/tw00009911.png"
  },
  {
    "id": "9912",
    "url": "https://asia.pokemon-card.com/tw/card-search/detail/9912/",
    "imgUrl": "https://asia.pokemon-card.com/tw/card-img/tw00009912.png"
  },
  {
    "id": "10221",
    "url": "https://asia.pokemon-card.com/tw/card-search/detail/10221/",
    "imgUrl": "https://asia.pokemon-card.com/tw/card-img/tw00010221.png"
  },
  {
    "id": "10222",
    "url": "https://asia.pokemon-card.com/tw/card-search/detail/10222/",
    "imgUrl": "https://asia.pokemon-card.com/tw/card-img/tw00010222.png"
  },
  {
    "id": "10223",
    "url": "https://asia.pokemon-card.com/tw/card-search/detail/10223/",
    "imgUrl": "https://asia.pokemon-card.com/tw/card-img/tw00010223.png"
  },
  {
    "id": "10224",
    "url": "https://asia.pokemon-card.com/tw/card-search/detail/10224/",
    "imgUrl": "https://asia.pokemon-card.com/tw/card-img/tw00010224.png"
  },
  {
    "id": "10225",
    "url": "https://asia.pokemon-card.com/tw/card-search/detail/10225/",
    "imgUrl": "https://asia.pokemon-card.com/tw/card-img/tw00010225.png"
  },
  {
    "id": "10226",
    "url": "https://asia.pokemon-card.com/tw/card-search/detail/10226/",
    "imgUrl": "https://asia.pokemon-card.com/tw/card-img/tw00010226.png"
  },
  {
    "id": "10227",
    "url": "https://asia.pokemon-card.com/tw/card-search/detail/10227/",
    "imgUrl": "https://asia.pokemon-card.com/tw/card-img/tw00010227.png"
  },
  {
    "id": "10228",
    "url": "https://asia.pokemon-card.com/tw/card-search/detail/10228/",
    "imgUrl": "https://asia.pokemon-card.com/tw/card-img/tw00010228.png"
  },
  {
    "id": "10229",
    "url": "https://asia.pokemon-card.com/tw/card-search/detail/10229/",
    "imgUrl": "https://asia.pokemon-card.com/tw/card-img/tw00010229.png"
  },
  {
    "id": "10230",
    "url": "https://asia.pokemon-card.com/tw/card-search/detail/10230/",
    "imgUrl": "https://asia.pokemon-card.com/tw/card-img/tw00010230.png"
  },
  {
    "id": "10231",
    "url": "https://asia.pokemon-card.com/tw/card-search/detail/10231/",
    "imgUrl": "https://asia.pokemon-card.com/tw/card-img/tw00010231.png"
  },
  {
    "id": "10232",
    "url": "https://asia.pokemon-card.com/tw/card-search/detail/10232/",
    "imgUrl": "https://asia.pokemon-card.com/tw/card-img/tw00010232.png"
  },
  {
    "id": "10233",
    "url": "https://asia.pokemon-card.com/tw/card-search/detail/10233/",
    "imgUrl": "https://asia.pokemon-card.com/tw/card-img/tw00010233.png"
  },
  {
    "id": "10234",
    "url": "https://asia.pokemon-card.com/tw/card-search/detail/10234/",
    "imgUrl": "https://asia.pokemon-card.com/tw/card-img/tw00010234.png"
  },
  {
    "id": "10235",
    "url": "https://asia.pokemon-card.com/tw/card-search/detail/10235/",
    "imgUrl": "https://asia.pokemon-card.com/tw/card-img/tw00010235.png"
  },
  {
    "id": "10236",
    "url": "https://asia.pokemon-card.com/tw/card-search/detail/10236/",
    "imgUrl": "https://asia.pokemon-card.com/tw/card-img/tw00010236.png"
  },
  {
    "id": "10237",
    "url": "https://asia.pokemon-card.com/tw/card-search/detail/10237/",
    "imgUrl": "https://asia.pokemon-card.com/tw/card-img/tw00010237.png"
  },
  {
    "id": "10238",
    "url": "https://asia.pokemon-card.com/tw/card-search/detail/10238/",
    "imgUrl": "https://asia.pokemon-card.com/tw/card-img/tw00010238.png"
  },
  {
    "id": "10239",
    "url": "https://asia.pokemon-card.com/tw/card-search/detail/10239/",
    "imgUrl": "https://asia.pokemon-card.com/tw/card-img/tw00010239.png"
  },
  {
    "id": "10240",
    "url": "https://asia.pokemon-card.com/tw/card-search/detail/10240/",
    "imgUrl": "https://asia.pokemon-card.com/tw/card-img/tw00010240.png"
  },
  {
    "id": "10241",
    "url": "https://asia.pokemon-card.com/tw/card-search/detail/10241/",
    "imgUrl": "https://asia.pokemon-card.com/tw/card-img/tw00010241.png"
  },
  {
    "id": "10242",
    "url": "https://asia.pokemon-card.com/tw/card-search/detail/10242/",
    "imgUrl": "https://asia.pokemon-card.com/tw/card-img/tw00010242.png"
  },
  {
    "id": "10243",
    "url": "https://asia.pokemon-card.com/tw/card-search/detail/10243/",
    "imgUrl": "https://asia.pokemon-card.com/tw/card-img/tw00010243.png"
  },
  {
    "id": "10244",
    "url": "https://asia.pokemon-card.com/tw/card-search/detail/10244/",
    "imgUrl": "https://asia.pokemon-card.com/tw/card-img/tw00010244.png"
  },
  {
    "id": "10245",
    "url": "https://asia.pokemon-card.com/tw/card-search/detail/10245/",
    "imgUrl": "https://asia.pokemon-card.com/tw/card-img/tw00010245.png"
  },
  {
    "id": "10246",
    "url": "https://asia.pokemon-card.com/tw/card-search/detail/10246/",
    "imgUrl": "https://asia.pokemon-card.com/tw/card-img/tw00010246.png"
  }
]